vmproto/__init__.py
vmproto/encryption.py
vmproto/transport.py
vmproto-0.9.0.dist-info/METADATA
vmproto-0.9.0.dist-info/WHEEL
vmproto-0.9.0.dist-info/top_level.txt
vmproto-0.9.0.dist-info/RECORD
