Metadata-Version: 2.4
Name: vmproto
Version: 0.9.0
Summary: A secure communication protocol for e2ee.
Author: Alfisene Keita
License: MIT
Classifier: Development Status :: 3 - Alpha
Classifier: Intended Audience :: Developers
Classifier: License :: OSI Approved :: MIT License
Classifier: Programming Language :: Python :: 3
Classifier: Programming Language :: Python :: 3.6
Classifier: Programming Language :: Python :: 3.7
Classifier: Programming Language :: Python :: 3.8
Classifier: Programming Language :: Python :: 3.9
Dynamic: author
Dynamic: classifier
Dynamic: license
Dynamic: summary
